gpstofile/__init__.py
gpstofile/__main__.py
gpstofile/gpstofile.py
gpstofile-0.0.6.dist-info/LICENSE
gpstofile-0.0.6.dist-info/METADATA
gpstofile-0.0.6.dist-info/WHEEL
gpstofile-0.0.6.dist-info/top_level.txt
gpstofile-0.0.6.dist-info/RECORD
