Metadata-Version: 2.1
Name: gpstofile
Version: 0.0.6
Summary: Quick and easy way to read GPS sentences to file with no gpsd required.
Home-page: https://github.com/pubudeux/gpstofile
Author: pubudeux
Project-URL: Documentation, https://github.com/pubudeux/gpstofile
Project-URL: Bug Reports, https://github.com/pubudeux/gpstofile/issues
Project-URL: Source Code, https://github.com/pubudeux/gpstofile
Keywords: gps,serial,gpsd,gps sentences
Classifier: Development Status :: 3 - Alpha
Classifier: Intended Audience :: Developers
Classifier: Programming Language :: Python :: 3.7
Classifier: Programming Language :: Python :: 3.8
Classifier: Programming Language :: Python :: 3.9
Classifier: Programming Language :: Python :: 3 :: Only
Classifier: License :: OSI Approved :: MIT License
Classifier: Operating System :: OS Independent
Requires-Python: >=3.7
License-File: LICENSE
Provides-Extra: dev
Requires-Dist: check-manifest ; extra == 'dev'
